hbsir/__init__.py
hbsir/api.py
hbsir/calculate.py
hbsir/maintainer.py
hbsir/config/settings.yaml
hbsir/internal_data/census_household_count.csv
hbsir/internal_data/nnftri_calorie_requirements.csv
hbsir/internal_data/province_weights_1371.csv
hbsir/internal_data/province_weights_1373.csv
hbsir/knowledge_base/__init__.py
hbsir/knowledge_base/minute_summary/v0.py
hbsir/knowledge_base/minute_summary/v0_metadata.yaml
hbsir/knowledge_base/sci_results/T101.py
hbsir/knowledge_base/sci_results/T102.py
hbsir/knowledge_base/sci_results/T103.py
hbsir/knowledge_base/sci_results/T104.py
hbsir/knowledge_base/sci_results/T105.py
hbsir/knowledge_base/sci_results/T106.py
hbsir/knowledge_base/sci_results/T116.py
hbsir/knowledge_base/sci_results/__init__.py
hbsir/knowledge_base/sci_results/common.py
hbsir/metadata/commodities.yaml
hbsir/metadata/id_information.yaml
hbsir/metadata/raw_files.yaml
hbsir/metadata/schema.yaml
hbsir/metadata/tables.yaml
hbsir/schema_functions/calorie_requirements.py
hbsir/schema_functions/standard_tables.py
hbsir/schema_functions/weight.py
hbsir/schema_functions/years_of_schooling.py
hbsir-0.6.6.dist-info/licenses/LICENCE
hbsir-0.6.6.dist-info/.gitignore
hbsir-0.6.6.dist-info/METADATA
hbsir-0.6.6.dist-info/WHEEL
hbsir-0.6.6.dist-info/top_level.txt
hbsir-0.6.6.dist-info/RECORD
