Metadata-Version: 2.4
Name: hbsir
Version: 0.6.6
Summary: An intuitive platform designed to simplify the analysis of Iran household budget survey data.
Author-email: Mohammad Amin Alavian <m.amin.alavian@gmail.com>
Project-URL: Homepage, https://github.com/Iran-Open-Data/HBSIR
Project-URL: Repository, https://github.com/Iran-Open-Data/HBSIR
Keywords: iran,survey,data,socioeconomic
Requires-Python: >=3.10
License-File: LICENCE
Requires-Dist: bssir>=0.6.7
Provides-Extra: all
Requires-Dist: bssir[all]; extra == "all"
Provides-Extra: dev
Requires-Dist: bssir[dev]; extra == "dev"
Provides-Extra: maintain
Requires-Dist: bssir[maintain]; extra == "maintain"
Provides-Extra: notebook
Requires-Dist: bssir[notebook]; extra == "notebook"
Provides-Extra: plot
Requires-Dist: bssir[plot]; extra == "plot"
Dynamic: license-file
